fetcher.py
fetcher_functions.py
fetcher_functions-1.1.dist-info/METADATA
fetcher_functions-1.1.dist-info/WHEEL
fetcher_functions-1.1.dist-info/top_level.txt
fetcher_functions-1.1.dist-info/RECORD
